[
	{
		"__TYPE__": "SharedSliceContent",
		"variation": "default",
		"primary": {
			"title": {
				"__TYPE__": "StructuredTextContent",
				"value": [
					{
						"type": "heading2",
						"content": {
							"text": "Separate"
						}
					}
				]
			},
			"subtitle": {
				"__TYPE__": "StructuredTextContent",
				"value": [
					{
						"type": "heading5",
						"content": {
							"text": "Victory"
						}
					}
				]
			},
			"image": {
				"origin": {
					"id": "main",
					"url": "https://images.unsplash.com/photo-1560457079-9a6532ccb118",
					"width": 4160,
					"height": 3120
				},
				"url": "https://images.unsplash.com/photo-1560457079-9a6532ccb118?rect=0%2C670%2C4160%2C1780&w=1400&h=599",
				"width": 1400,
				"height": 599,
				"edit": {
					"zoom": 1,
					"crop": {
						"x": 0,
						"y": 670
					},
					"background": "transparent"
				},
				"credits": null,
				"alt": null,
				"__TYPE__": "ImageContent",
				"thumbnails": {
					"mobile": {
						"origin": {
							"id": "mobile",
							"url": "https://images.unsplash.com/photo-1579931794097-0ad001e51edb",
							"width": 3958,
							"height": 3958
						},
						"url": "https://images.unsplash.com/photo-1579931794097-0ad001e51edb?rect=0%2C0%2C3958%2C3958&w=320&h=320",
						"width": 320,
						"height": 320,
						"edit": {
							"zoom": 1,
							"crop": {
								"x": 0,
								"y": 0
							},
							"background": "transparent"
						},
						"credits": null,
						"alt": null
					}
				}
			}
		},
		"items": []
	},
	{
		"__TYPE__": "SharedSliceContent",
		"variation": "heroWithButton",
		"primary": {
			"title": {
				"__TYPE__": "StructuredTextContent",
				"value": [
					{
						"type": "heading2",
						"content": {
							"text": "Zipper"
						}
					}
				]
			},
			"subtitle": {
				"__TYPE__": "StructuredTextContent",
				"value": [
					{
						"type": "heading5",
						"content": {
							"text": "Order"
						}
					}
				]
			},
			"image": {
				"origin": {
					"id": "main",
					"url": "https://images.unsplash.com/photo-1579931794097-0ad001e51edb",
					"width": 3958,
					"height": 3958
				},
				"url": "https://images.unsplash.com/photo-1579931794097-0ad001e51edb?rect=0%2C1272%2C3958%2C1414&w=1400&h=500",
				"width": 1400,
				"height": 500,
				"edit": {
					"zoom": 1,
					"crop": {
						"x": 0,
						"y": 1272
					},
					"background": "transparent"
				},
				"credits": null,
				"alt": null,
				"__TYPE__": "ImageContent",
				"thumbnails": {
					"mobile": {
						"origin": {
							"id": "mobile",
							"url": "https://images.unsplash.com/photo-1576662712957-9c79ae1280f8",
							"width": 3456,
							"height": 3456
						},
						"url": "https://images.unsplash.com/photo-1576662712957-9c79ae1280f8?rect=0%2C0%2C3456%2C3456&w=320&h=320",
						"width": 320,
						"height": 320,
						"edit": {
							"zoom": 1,
							"crop": {
								"x": 0,
								"y": 0
							},
							"background": "transparent"
						},
						"credits": null,
						"alt": null
					}
				}
			},
			"cta_link": {
				"__TYPE__": "LinkContent",
				"value": {
					"__TYPE__": "ExternalLink",
					"url": "https://prismic.io",
					"text": "sound"
				}
			},
			"cta_label": {
				"__TYPE__": "FieldContent",
				"value": "comfortable",
				"type": "Text"
			}
		},
		"items": [
			{
				"__TYPE__": "GroupItemContent",
				"value": []
			}
		]
	}
]