[
	{
		"__TYPE__": "SharedSliceContent",
		"variation": "primary",
		"primary": {
			"label": {
				"__TYPE__": "FieldContent",
				"value": "master",
				"type": "Text"
			},
			"link": {
				"__TYPE__": "LinkContent",
				"value": {
					"__TYPE__": "ExternalLink",
					"url": "http://google.com",
					"text": "knife"
				}
			}
		},
		"items": [
			{
				"__TYPE__": "GroupItemContent",
				"value": []
			}
		]
	},
	{
		"__TYPE__": "SharedSliceContent",
		"variation": "secondary",
		"primary": {
			"label": {
				"__TYPE__": "FieldContent",
				"value": "realize",
				"type": "Text"
			},
			"link": {
				"__TYPE__": "LinkContent",
				"value": {
					"__TYPE__": "ExternalLink",
					"url": "http://google.com",
					"text": "yourself"
				}
			}
		},
		"items": [
			{
				"__TYPE__": "GroupItemContent",
				"value": []
			}
		]
	}
]